loznxiaoai-0.1.0.dist-info/METADATA
loznxiaoai-0.1.0.dist-info/WHEEL
loznxiaoai-0.1.0.dist-info/entry_points.txt
loznxiaoai-0.1.0.dist-info/licenses/LICENSE
xiaogpt/__init__.py
xiaogpt/__main__.py
xiaogpt/bot/__init__.py
xiaogpt/bot/base_bot.py
xiaogpt/bot/chatgptapi_bot.py
xiaogpt/bot/gpt3_bot.py
xiaogpt/bot/newbing_acheongbot.py
xiaogpt/bot/newbing_bot.py
xiaogpt/bot/revchatgpt_bot.py
xiaogpt/cli.py
xiaogpt/config.py
xiaogpt/utils.py
xiaogpt/xiaogpt.py
loznxiaoai-0.1.0.dist-info/RECORD
