Metadata-Version: 2.1
Name: loznxiaoai
Version: 0.1.0
Summary: Play ChatGPT with xiaomi AI speaker
Author-Email: lozn <qssq521@gmail.com>
License: MIT
Classifier: License :: OSI Approved :: MIT License
Classifier: Operating System :: OS Independent
Classifier: Programming Language :: Python :: 3
Project-URL: Homepage, https://github.com/qssq/xiaoai
Requires-Python: >=3.7.1
Requires-Dist: miservice_fork
Requires-Dist: openai
Requires-Dist: aiohttp
Requires-Dist: rich
Requires-Dist: edge-tts>=6.1.3
Requires-Dist: EdgeGPT
